Metadata-Version: 2.1
Name: btlewrap
Version: 0.1.1
Summary: wrapper around different bluetooth low energy backends
Home-page: https://github.com/ChristianKuehnel/btlewrap
Author: Christian Kuehnel
Author-email: christian.kuehnel@gmail.com
License: MIT
Keywords: bluetooth low-energy ble
Platform: UNKNOWN
Classifier: Development Status :: 4 - Beta
Classifier: Intended Audience :: Developers
Classifier: Topic :: System :: Hardware :: Hardware Drivers
Classifier: License :: OSI Approved :: MIT License
Classifier: Programming Language :: Python :: 3
Classifier: Programming Language :: Python :: 3.6
Classifier: Programming Language :: Python :: 3.7
Classifier: Programming Language :: Python :: 3.8
Classifier: Programming Language :: Python :: 3.9
Classifier: Programming Language :: Python :: 3.10
Provides-Extra: testing
Provides-Extra: bluepy
Provides-Extra: pygatt
License-File: LICENSE
